orgcrawler/payload/config.py
orgcrawler/payload/iam.py
orgcrawler/payload/route53.py
orgcrawler/payload/s3.py
orgcrawler/untested_payload/cloudformation.py
orgcrawler/untested_payload/cloudtrail.py
orgcrawler/untested_payload/config.py
orgcrawler/untested_payload/ec2.py
orgcrawler/untested_payload/iam.py
orgcrawler/untested_payload/securityhub.py
orgcrawler.payload-0.0.1.dist-info/LICENSE
orgcrawler.payload-0.0.1.dist-info/METADATA
orgcrawler.payload-0.0.1.dist-info/WHEEL
orgcrawler.payload-0.0.1.dist-info/top_level.txt
orgcrawler.payload-0.0.1.dist-info/RECORD
